{
  "params": {
    "random_seed": 7010,
    "shelf_levels": 4,
    "shelf_width": 0.783,
    "shelf_depth": 0.299,
    "shelf_center_x": 0.879,
    "shelf_center_y": -0.102,
    "shelf_bottom_z": 0.498,
    "shelf_level_gap": 0.278,
    "shelf_board_thickness": 0.025,
    "shelf_side_thickness": 0.059,
    "shelf_back_thickness": 0.043,
    "target_depth_ratio": 0.068,
    "target_lateral_margin": 0.08,
    "target_lateral_span": 0.094,
    "target_box_size_x": 0.086,
    "target_box_size_y": 0.107,
    "target_box_size_z": 0.085,
    "clutter_count": 0,
    "target_gap_index": 1,
    "target_level": 2
  },
  "derived": {
    "target_box": {
      "center": [
        0.9324999999999999,
        -0.021999999999999992,
        1.109
      ],
      "size": [
        0.086,
        0.107,
        0.085
      ]
    },
    "clutter_boxes": [],
    "target_pose": {
      "position": {
        "x": 0.744868,
        "y": -0.018434,
        "z": 0.915
      },
      "orientation": {
        "x": 0.0,
        "y": 0.0,
        "z": 0.0,
        "w": 1.0
      }
    },
    "inner_front_x": 0.7295,
    "back_panel_front_x": 0.9855
  }
}
